{
  "elements": [
      {
          "to~": {
              "lastName": {
                  "localized": {
                      "en_US": "Belchgit er"
                  },
                  "preferredLocale": {
                      "country": "US",
                      "language": "en"
                  }
              },
              "firstName": {
                  "localized": {
                      "en_US": "Louise"
                  },
                  "preferredLocale": {
                      "country": "US",
                      "language": "en"
                  }
              },
              "id": "9HfhE6QlBz"
          },
          "to": "urn:li:person:9HfhE6QlBz"
      },
      {
        "to~": {
          "lastName": {
              "localized": {
                  "en_US": "Robbie"
              },
              "preferredLocale": {
                  "country": "US",
                  "language": "en"
              }
          },
          "firstName": {
              "localized": {
                  "en_US": "Margot"
              },
              "preferredLocale": {
                  "country": "US",
                  "language": "en"
              }
          },
          "id": "9HfhE6QlBA"
      },
      "to": "urn:li:person:9HfhE6QlBA"
    }

  ],
  "paging": {
    "total": 2,
    "count": 10,
    "start": 0,
    "links": []
  }
}